genai_perf/.gitignore
genai_perf/__init__.py
genai_perf/constants.py
genai_perf/exceptions.py
genai_perf/logging.py
genai_perf/main.py
genai_perf/parser.py
genai_perf/tokenizer.py
genai_perf/types.py
genai_perf/utils.py
genai_perf/checkpoint/checkpoint.py
genai_perf/config/endpoint_config.py
genai_perf/config/model_spec.py
genai_perf/config/generate/genai_perf_config.py
genai_perf/config/generate/objective_parameter.py
genai_perf/config/generate/perf_analyzer_config.py
genai_perf/config/generate/search_parameter.py
genai_perf/config/generate/search_parameters.py
genai_perf/config/generate/sweep_objective_generator.py
genai_perf/config/input/base_config.py
genai_perf/config/input/config_analyze.py
genai_perf/config/input/config_command.py
genai_perf/config/input/config_defaults.py
genai_perf/config/input/config_endpoint.py
genai_perf/config/input/config_field.py
genai_perf/config/input/config_input.py
genai_perf/config/input/config_output.py
genai_perf/config/input/config_perf_analyzer.py
genai_perf/config/input/config_process.py
genai_perf/config/input/config_tokenizer.py
genai_perf/config/input/create_config.py
genai_perf/config/run/results.py
genai_perf/config/run/run_config.py
genai_perf/export_data/console_exporter.py
genai_perf/export_data/csv_exporter.py
genai_perf/export_data/data_exporter_factory.py
genai_perf/export_data/data_exporter_interface.py
genai_perf/export_data/exporter_config.py
genai_perf/export_data/exporter_utils.py
genai_perf/export_data/json_exporter.py
genai_perf/export_data/output_reporter.py
genai_perf/export_data/telemetry_data_exporter_util.py
genai_perf/goodput_calculator/__init__.py
genai_perf/goodput_calculator/goodput_calculator.py
genai_perf/goodput_calculator/llm_goodput_calculator.py
genai_perf/inputs/__init__.py
genai_perf/inputs/input_constants.py
genai_perf/inputs/inputs.py
genai_perf/inputs/inputs_config.py
genai_perf/inputs/converters/__init__.py
genai_perf/inputs/converters/base_converter.py
genai_perf-0.0.15.post1.dist-info/METADATA
genai_perf-0.0.15.post1.dist-info/WHEEL
genai_perf-0.0.15.post1.dist-info/entry_points.txt
genai_perf-0.0.15.post1.dist-info/licenses/LICENSE
genai_perf-0.0.15.post1.dist-info/RECORD
