Metadata-Version: 2.4
Name: genai-perf
Version: 0.0.15.post1
Summary: GenAI Perf Analyzer CLI - CLI tool to simplify profiling LLMs and Generative AI models with Perf Analyzer
Project-URL: Homepage, https://github.com/triton-inference-server/perf_analyzer
Project-URL: Bug Tracker, https://github.com/triton-inference-server/perf_analyzer/issues
License: BSD
License-File: LICENSE
Classifier: Development Status :: 3 - Alpha
Classifier: Intended Audience :: Developers
Classifier: Intended Audience :: Science/Research
Classifier: Operating System :: Unix
Classifier: Programming Language :: Python
Classifier: Programming Language :: Python :: 3
Classifier: Programming Language :: Python :: 3.10
Classifier: Programming Language :: Python :: 3.12
Classifier: Topic :: Scientific/Engineering
Classifier: Topic :: Software Development
Requires-Python: <4,>=3.10
Requires-Dist: fastparquet
Requires-Dist: jinja2
Requires-Dist: kaleido
Requires-Dist: numpy
Requires-Dist: optuna==3.6.1
Requires-Dist: orjson
Requires-Dist: pandas
Requires-Dist: perf-analyzer
Requires-Dist: pillow
Requires-Dist: plotly
Requires-Dist: pyarrow
Requires-Dist: pytest
Requires-Dist: pytest-mock
Requires-Dist: pyyaml
Requires-Dist: responses
Requires-Dist: rich
Requires-Dist: soundfile
Requires-Dist: statsmodels
Requires-Dist: transformers
